src/__init__.py
src/ali_agentic_adk_python/__init__.py
src/ali_agentic_adk_python/temp
src/ali_agentic_adk_python/core/__init__.py
src/ali_agentic_adk_python/core/common/__init__.py
src/ali_agentic_adk_python/core/common/role.py
src/ali_agentic_adk_python/core/dto/__init__.py
src/ali_agentic_adk_python/core/dto/dashscope_message.py
src/ali_agentic_adk_python/core/dto/function.py
src/ali_agentic_adk_python/core/model/__init__.py
src/ali_agentic_adk_python/core/model/basic_llm.py
src/ali_agentic_adk_python/core/model/dashscope_llm.py
src/ali_agentic_adk_python/core/tool/__init__.py
src/ali_agentic_adk_python/core/tool/dashscope_app_tool.py
src/ali_agentic_adk_python/core/utils/__init__.py
src/ali_agentic_adk_python/core/utils/dashscope_message_convert_utils.py
src/ali_agentic_adk_python/core/utils/dashscope_utils.py
src/ali_agentic_adk_python/core/utils/prompt_utils.py
src/ali_agentic_adk_python/extension/__init__.py
src/ali_agentic_adk_python/extension/web/__init__.py
src/ali_agentic_adk_python/extension/web/app.py
src/ali_agentic_adk_python/extension/web/starter.py
src/ali_agentic_adk_python/extension/web/configuration/__init__.py
src/ali_agentic_adk_python/extension/web/configuration/browser_agent_register.py
src/ali_agentic_adk_python/extension/web/configuration/browser_runner_service.py
src/ali_agentic_adk_python/extension/web/configuration/browser_use_configuration.py
src/ali_agentic_adk_python/extension/web/controllers/__init__.py
src/ali_agentic_adk_python/extension/web/controllers/browser_use_callback_controller.py
src/ali_agentic_adk_python/extension/web/controllers/browser_use_dev_controller.py
src/ali_agentic_adk_python/extension/web/controllers/browser_use_resource_controller.py
src/ali_agentic_adk_python/extension/web/controllers/browser_use_static_controller.py
src/ali_agentic_adk_python/extension/web/domain/__init__.py
src/ali_agentic_adk_python/extension/web/domain/models.py
src/ali_agentic_adk_python/extension/web/dto/__init__.py
ali_agentic_adk_python-0.0.2.dist-info/METADATA
ali_agentic_adk_python-0.0.2.dist-info/WHEEL
ali_agentic_adk_python-0.0.2.dist-info/licenses/LICENSE
ali_agentic_adk_python-0.0.2.dist-info/RECORD
