Metadata-Version: 2.4
Name: ali_agentic_adk_python
Version: 0.0.2
Author-email: AIDC <mengyu.smy@alibaba-inc.com>
License-Expression: MIT
License-File: LICENSE
Requires-Python: >=3.10
Requires-Dist: aiohttp
Requires-Dist: alibabacloud-appstream-center20210218
Requires-Dist: alibabacloud-ecd20200930
Requires-Dist: alibabacloud-ecd20201002
Requires-Dist: alibabacloud-eds-aic20230930
Requires-Dist: dashscope
Requires-Dist: google-adk
Requires-Dist: openai
